buildai_pro/__init__.py
buildai_pro/activations.py
buildai_pro/data.py
buildai_pro/io.py
buildai_pro/losses.py
buildai_pro/nn.py
buildai_pro/optim.py
buildai_pro/tensor.py
buildai_pro/train.py
buildai_pro/examples/__init__.py
buildai_pro/examples/train_text_classifier.py
buildai_pro-1.0.2.dist-info/METADATA
buildai_pro-1.0.2.dist-info/WHEEL
buildai_pro-1.0.2.dist-info/top_level.txt
buildai_pro-1.0.2.dist-info/RECORD
