Metadata-Version: 2.4
Name: BuildAi_pro
Version: 1.0.2
Summary: Improved BuildAi: lightweight educational deep-learning toolkit.
Author-email: no thank you <you@example.com>
License: MIT
Classifier: Programming Language :: Python :: 3
Classifier: License :: OSI Approved :: MIT License
Classifier: Operating System :: OS Independent
Requires-Python: >=3.8
Requires-Dist: numpy
